__init__.py
parallel_calls/__init__.py
parallel_calls/core.py
parallel_rest_calls-1.0.0.dist-info/METADATA
parallel_rest_calls-1.0.0.dist-info/WHEEL
parallel_rest_calls-1.0.0.dist-info/top_level.txt
parallel_rest_calls-1.0.0.dist-info/RECORD
