Metadata-Version: 2.1
Name: parallel-rest-calls
Version: 1.0.0
Summary: Tools to easily parallelize GET http calls to REST resource endpoints
Author-email: Ram Newton A <ramnewton.a@gmail.com>
Keywords: paralellism,requests,rest
Requires-Dist: requests
Provides-Extra: dev
Requires-Dist: black ; extra == 'dev'
Requires-Dist: bumpver ; extra == 'dev'
Requires-Dist: pip-tools ; extra == 'dev'
Requires-Dist: requests-mock (>=1.9.3) ; extra == 'dev'
Requires-Dist: pytest ; extra == 'dev'
